{"game_id":916,"wiki_id":"B144","category":"sortie","frequency":"onetime","prereqs":[292],"requirements":{"category":"sortie","map":["5-1","5-2","5-3","5-4","5-5"],"boss":true,"result":"S","comp":[{"ship_id":592,"amount":1},{"ship_id":[78,79,85],"amount":1},{"class_id":3,"amount":1},{"class_id":2,"amount":[1,99]}],"times":1},"rewards":{"resources":[1942,2020,0,0],"other":[{"choices":[{"category":"equipment","id":204,"stars":2,"amount":1},{"category":"equipment","id":238,"stars":2,"amount":1},{"category":"inventory","id":78,"amount":1}]},{"choices":[{"category":"equipment","id":329,"amount":1},{"category":"inventory","id":75,"amount":2}]}]}}