{
  "game_id": 123,
  "wiki_id": "A23",
  "category": "composition",
  "frequency": "onetime",
  "updated": "2024-02-01T07:24:01.3464596Z",
  "prereqs": [
    122
  ],
  "requirements": {
    "category": "fleet",
    "fleet_id": 1,
    "comp": [
      {
        "ship_id": [
          110,
          111
        ],
        "amount": 2
      },
      {
        "class_id": 2,
        "amount": 2
      },
      {
        "otherships": true,
        "amount": [
          0,
          2
        ]
      }
    ]
  },
  "rewards": {
    "resources": [
      300,
      0,
      0,
      300
    ],
    "other": [
      {
        "category": "equipment",
        "id": 42,
        "amount": 1
      }
    ]
  }
}