{
  "game_id": 836,
  "wiki_id": "B85",
  "category": "sortie",
  "frequency": "onetime",
  "release_date": "2016-11-04",
  "updated": "2024-02-09T08:36:57.7865386Z",
  "prereqs": [
    179
  ],
  "requirements": {
    "category": "sortie",
    "sortie": [
      {
        "map": "2-5",
        "boss": true,
        "result": "S",
        "times": 1
      }
    ],
    "comp": [
      {
        "ship_id": 487,
        "position": 1
      },
      {
        "ship_id": [
          119,
          118,
          264,
          99,
          208,
          368
        ],
        "amount": 5
      }
    ]
  },
  "rewards": {
    "resources": [
      600,
      600,
      0,
      0
    ],
    "other": [
      {
        "category": "equipment",
        "id": 193,
        "amount": 1
      }
    ]
  }
}